Calculator/__init__.py
Calculator/core.py
calculator2-0.1.0.dist-info/licenses/LICENSE
calculator2-0.1.0.dist-info/METADATA
calculator2-0.1.0.dist-info/WHEEL
calculator2-0.1.0.dist-info/top_level.txt
calculator2-0.1.0.dist-info/RECORD
